MANIFEST.in
README.md
setup.py
btbpy/__init__.py
btbpy/algo_smooth.cpp
btbpy/algo_smooth.pyx
btbpy/createGrid.py
btbpy/kernelSmoothing.py
btbpy.egg-info/PKG-INFO
btbpy.egg-info/SOURCES.txt
btbpy.egg-info/dependency_links.txt
btbpy.egg-info/not-zip-safe
btbpy.egg-info/requires.txt
btbpy.egg-info/top_level.txt
btbpy/data/commune_reg_04_2018.dbf
btbpy/data/commune_reg_04_2018.prj
btbpy/data/commune_reg_04_2018.shp
btbpy/data/commune_reg_04_2018.shx
btbpy/data/dfPrix_SP95_2016.csv
btbpy/data/fr_metro_grid1km.csv
btbpy/data/reunion_emprise_grid200m_epsg32740.csv
btbpy/data/reunion_epsg32740.csv
btbpy/data/reunion_grid200m_epsg32740.csv