Metadata-Version: 2.1
Name: btbpy
Version: 0.1.0
Summary: Smooth geographical data
Home-page: https://gitlab.com/mrteste/btbpy
Author: Julien Jamme, Arlindo Dos Santos, François Sémécurbe
Maintainer: Julien Jamme
Maintainer-email: julien.jamme@protonmail.com
License: GPL3
Keywords: smooth greographic kernel smoothing
Platform: UNKNOWN
Classifier: Development Status :: 5 - Production/Stable
Classifier: Programming Language :: Python :: 3
Classifier: Programming Language :: Cython
Classifier: License :: OSI Approved :: GNU General Public License v3 (GPLv3)
Classifier: Operating System :: OS Independent
